spectomate/__init__.py
spectomate/__main__.py
spectomate/_version.py
spectomate/cli.py
spectomate/format_cli.py
spectomate/git_cli.py
spectomate/mypy_cli.py
spectomate/test_cli.py
spectomate/update_cli.py
spectomate/converters/__init__.py
spectomate/converters/conda_to_pip.py
spectomate/converters/external_converters.py
spectomate/converters/pip_to_conda.py
spectomate/converters/pip_to_pdm.py
spectomate/converters/pip_to_pipenv.py
spectomate/converters/pip_to_poetry.py
spectomate/converters/poetry_to_conda.py
spectomate/converters/poetry_to_pip.py
spectomate/core/__init__.py
spectomate/core/base_converter.py
spectomate/core/mypy_helper.py
spectomate/core/registry.py
spectomate/core/utils.py
spectomate/schemas/__init__.py
spectomate/schemas/conda_schema.py
spectomate/schemas/pip_schema.py
spectomate/schemas/pipenv_schema.py
spectomate/schemas/poetry_schema.py
spectomate-0.1.66.dist-info/licenses/LICENSE
spectomate-0.1.66.dist-info/METADATA
spectomate-0.1.66.dist-info/WHEEL
spectomate-0.1.66.dist-info/entry_points.txt
spectomate-0.1.66.dist-info/top_level.txt
spectomate-0.1.66.dist-info/RECORD
