Metadata-Version: 2.4
Name: spectomate
Version: 0.1.66
Summary: Modularny konwerter formatów pakietów Python
Author-email: Tom Sapletta <info@spectomate.com>
License:                                  Apache License
Project-URL: Homepage, https://github.com/spectomate/python
Project-URL: Bug Tracker, https://github.com/spectomate/python/issues
Project-URL: Documentation, https://spectomate.readthedocs.io
Keywords: conda,pip,poetry,pipenv,pdm,package,converter
Classifier: Programming Language :: Python :: 3
Classifier: Programming Language :: Python :: 3.8
Classifier: Programming Language :: Python :: 3.9
Classifier: Programming Language :: Python :: 3.10
Classifier: Programming Language :: Python :: 3.11
Classifier: License :: OSI Approved :: MIT License
Classifier: Operating System :: OS Independent
Classifier: Development Status :: 4 - Beta
Classifier: Intended Audience :: Developers
Classifier: Topic :: Software Development :: Build Tools
Requires-Python: >=3.8
License-File: LICENSE
Requires-Dist: click>=8.0.0
Requires-Dist: pyyaml>=6.0
Requires-Dist: toml>=0.10.2
Requires-Dist: packaging>=21.0
Requires-Dist: tomli>=2.0.0
Requires-Dist: tomli-w>=1.0.0
Provides-Extra: external
Requires-Dist: dephell>=0.8.3; extra == "external"
Requires-Dist: req2toml>=0.1.0; extra == "external"
Requires-Dist: poetry2conda>=0.3.0; extra == "external"
Provides-Extra: dev
Requires-Dist: pytest>=7.0.0; extra == "dev"
Requires-Dist: black>=22.0.0; extra == "dev"
Requires-Dist: isort>=5.10.0; extra == "dev"
Requires-Dist: mypy>=0.950; extra == "dev"
Requires-Dist: flake8>=4.0.0; extra == "dev"
Requires-Dist: types-toml>=0.10.0; extra == "dev"
Requires-Dist: types-PyYAML>=6.0.0; extra == "dev"
Dynamic: license-file
